odoo/addons/l10n_es_aeat_sii_match/README.rst
odoo/addons/l10n_es_aeat_sii_match/__init__.py
odoo/addons/l10n_es_aeat_sii_match/__manifest__.py
odoo/addons/l10n_es_aeat_sii_match/i18n/es.po
odoo/addons/l10n_es_aeat_sii_match/i18n/l10n_es_aeat_sii_match.pot
odoo/addons/l10n_es_aeat_sii_match/migrations/13.0.1.0.0/post-migration.py
odoo/addons/l10n_es_aeat_sii_match/migrations/13.0.1.0.0/pre-migration.py
odoo/addons/l10n_es_aeat_sii_match/models/__init__.py
odoo/addons/l10n_es_aeat_sii_match/models/account_move.py
odoo/addons/l10n_es_aeat_sii_match/models/aeat_sii_match_difference.py
odoo/addons/l10n_es_aeat_sii_match/models/aeat_sii_match_report.py
odoo/addons/l10n_es_aeat_sii_match/readme/CONTRIBUTORS.rst
odoo/addons/l10n_es_aeat_sii_match/readme/DESCRIPTION.rst
odoo/addons/l10n_es_aeat_sii_match/security/aeat_sii.xml
odoo/addons/l10n_es_aeat_sii_match/security/ir.model.access.csv
odoo/addons/l10n_es_aeat_sii_match/static/description/icon.png
odoo/addons/l10n_es_aeat_sii_match/static/description/index.html
odoo/addons/l10n_es_aeat_sii_match/views/account_move_views.xml
odoo/addons/l10n_es_aeat_sii_match/views/aeat_sii_match_report.xml
odoo13_addon_l10n_es_aeat_sii_match-13.0.1.0.1.dev3.dist-info/METADATA
odoo13_addon_l10n_es_aeat_sii_match-13.0.1.0.1.dev3.dist-info/WHEEL
odoo13_addon_l10n_es_aeat_sii_match-13.0.1.0.1.dev3.dist-info/top_level.txt
odoo13_addon_l10n_es_aeat_sii_match-13.0.1.0.1.dev3.dist-info/RECORD
